palo_alto_firewall_analyzer/__init__.py
palo_alto_firewall_analyzer/core.py
palo_alto_firewall_analyzer/pan_api.py
palo_alto_firewall_analyzer/pan_config.py
palo_alto_firewall_analyzer/pan_helpers.py
palo_alto_firewall_analyzer/fixers/__init__.py
palo_alto_firewall_analyzer/fixers/consolidate_equivalent_objects.py
palo_alto_firewall_analyzer/fixers/delete_disabled_policies.py
palo_alto_firewall_analyzer/fixers/delete_unused_objects.py
palo_alto_firewall_analyzer/fixers/disable_shadowed_rules.py
palo_alto_firewall_analyzer/fixers/fix_UnqualifiedFQDN.py
palo_alto_firewall_analyzer/fixers/fix_bad_log_setting.py
palo_alto_firewall_analyzer/fixers/remove_redundant_rule_addresses.py
palo_alto_firewall_analyzer/fixers/remove_redundant_rule_services.py
palo_alto_firewall_analyzer/fixers/rename_unconventional_objects.py
palo_alto_firewall_analyzer/fixers/replace_ips_with_resolving_fqdns.py
palo_alto_firewall_analyzer/scripts/__init__.py
palo_alto_firewall_analyzer/scripts/pan_analyzer.py
palo_alto_firewall_analyzer/scripts/pan_categorization_lookup.py
palo_alto_firewall_analyzer/scripts/pan_delete_addresses.py
palo_alto_firewall_analyzer/scripts/pan_disable_rules.py
palo_alto_firewall_analyzer/scripts/pan_dump_active_sessions.py
palo_alto_firewall_analyzer/scripts/pan_run_command.py
palo_alto_firewall_analyzer/scripts/pan_zone_lookup.py
palo_alto_firewall_analyzer/validators/__init__.py
palo_alto_firewall_analyzer/validators/bad_group_profile.py
palo_alto_firewall_analyzer/validators/bad_hostnames.py
palo_alto_firewall_analyzer/validators/bad_log_setting.py
palo_alto_firewall_analyzer/validators/consolidatable_addresses_and_groups.py
palo_alto_firewall_analyzer/validators/consolidatable_service_and_groups.py
palo_alto_firewall_analyzer/validators/disabled_policies.py
palo_alto_firewall_analyzer/validators/equivalent_objects.py
palo_alto_firewall_analyzer/validators/fqdn_contains_ip.py
palo_alto_firewall_analyzer/validators/group_replacements.py
pan_analyzer-0.0.3.13.dist-info/licenses/LICENSE
pan_analyzer-0.0.3.13.dist-info/METADATA
pan_analyzer-0.0.3.13.dist-info/WHEEL
pan_analyzer-0.0.3.13.dist-info/entry_points.txt
pan_analyzer-0.0.3.13.dist-info/top_level.txt
pan_analyzer-0.0.3.13.dist-info/RECORD
