Metadata-Version: 2.4
Name: pan_analyzer
Version: 0.0.3.13
Summary: Detect and remediate configuration issues in Palo Alto Networks firewalls
Author-email: Moshe Kaplan <me@moshekaplan.com>
License: CC0 1.0 Universal
Project-URL: Homepage, https://github.com/moshekaplan/palo_alto_firewall_analyzer
Project-URL: Bug Tracker, https://github.com/moshekaplan/palo_alto_firewall_analyzer/issues
Classifier: Programming Language :: Python :: 3
Classifier: License :: CC0 1.0 Universal (CC0 1.0) Public Domain Dedication
Classifier: Operating System :: OS Independent
Classifier: Development Status :: 3 - Alpha
Classifier: Topic :: System :: Networking :: Firewalls
Requires-Python: >=3.7
License-File: LICENSE
Requires-Dist: requests
Requires-Dist: xmltodict
Provides-Extra: test
Requires-Dist: pytest; extra == "test"
Dynamic: license-file
